{
    "tb": {
        "Kisah Para Rasul 1": "1",
        "Kisah Para Rasul 2": "2",
        "Kisah Para Rasul 3": "3",
        "Kisah Para Rasul 4": "4",
        "Kisah Para Rasul 5": "5",
        "Kisah Para Rasul 6": "6",
        "Kisah Para Rasul 7": "7",
        "Kisah Para Rasul 8": "8",
        "Kisah Para Rasul 9": "9",
        "Kisah Para Rasul 10": "10",
        "Kisah Para Rasul 11": "11",
        "Kisah Para Rasul 12": "12",
        "Kisah Para Rasul 13": "13",
        "Kisah Para Rasul 14": "14",
        "Kisah Para Rasul 15": "15",
        "Kisah Para Rasul 16": "16",
        "Kisah Para Rasul 17": "17",
        "Kisah Para Rasul 18": "18",
        "Kisah Para Rasul 19": "19",
        "Kisah Para Rasul 20": "20",
        "Kisah Para Rasul 21": "21",
        "Kisah Para Rasul 22": "22",
        "Kisah Para Rasul 23": "23",
        "Kisah Para Rasul 24": "24",
        "Kisah Para Rasul 25": "25",
        "Kisah Para Rasul 26": "26",
        "Kisah Para Rasul 27": "27",
        "Kisah Para Rasul 28": "28"
    }
}